{"cameraMode":{"drawMode":0,"name":"Shaded","section":"Shading Mode"},"sceneLighting":true,"audioPlay":false,"sceneViewState":{"showFog":true,"showMaterialUpdate":false,"showSkybox":true,"showFlares":true,"showImageEffects":true,"showParticleSystems":true},"in2DMode":false,"pivot":{"x":-5.16470193862915,"y":2.446396827697754,"z":5.835821151733398},"rotation":{"x":-0.3030330538749695,"y":-0.11781342327594757,"z":0.037778764963150027,"w":-0.944914698600769},"size":3.147109270095825,"orthographic":false}