{"cameraMode":{"drawMode":0,"name":"Shaded","section":"Shading Mode"},"sceneLighting":true,"audioPlay":false,"sceneViewState":{"showFog":true,"showMaterialUpdate":false,"showSkybox":true,"showFlares":true,"showImageEffects":true,"showParticleSystems":true},"in2DMode":false,"pivot":{"x":-6.540036678314209,"y":2.8350772857666017,"z":1.366123914718628},"rotation":{"x":-0.1877017468214035,"y":0.012237570248544217,"z":-0.0023425929248332979,"w":-0.9821470379829407},"size":2.8578836917877199,"orthographic":false}